amiconn.py
amiconn-0.536.dist-info/METADATA
amiconn-0.536.dist-info/RECORD
amiconn-0.536.dist-info/WHEEL
amiconn-0.536.dist-info/top_level.txt
