Metadata-Version: 2.1
Name: amiconn
Version: 0.536
Summary: UNKNOWN
Home-page: UNKNOWN
Author: QiQi
Author-email: UNKNOWN
License: UNKNOWN
Platform: UNKNOWN
Requires-Dist: pyodbc
Requires-Dist: SQLAlchemy (>=0.98)
